{
  "sessionId": "session-1756503305758-gix90yfiu",
  "entries": [
    {
      "id": "evt-1756503305758-rmpln1w3m",
      "timestamp": "2025-08-29T21:35:05.759Z",
      "sessionId": "session-1756503305758-gix90yfiu",
      "type": "session_started",
      "severity": "info",
      "entity": "system",
      "action": "Session started",
      "triggeredBy": "system",
      "context": {
        "sessionId": "session-1756503305758-gix90yfiu",
        "timestamp": "2025-08-29T21:35:05.758Z"
      }
    },
    {
      "id": "evt-1756503305804-gzs40ixil",
      "timestamp": "2025-08-29T21:35:05.804Z",
      "sessionId": "session-1756503305758-gix90yfiu",
      "type": "configuration_changed",
      "severity": "debug",
      "entity": "discover",
      "action": "Tool registered",
      "triggeredBy": "system",
      "context": {
        "category": "discovery",
        "priority": 0
      }
    },
    {
      "id": "evt-1756503305804-91svmr0pq",
      "timestamp": "2025-08-29T21:35:05.804Z",
      "sessionId": "session-1756503305758-gix90yfiu",
      "type": "configuration_changed",
      "severity": "debug",
      "entity": "activate",
      "action": "Tool registered",
      "triggeredBy": "system",
      "context": {
        "category": "discovery",
        "priority": 0
      }
    },
    {
      "id": "evt-1756503305804-sn9smo3ln",
      "timestamp": "2025-08-29T21:35:05.804Z",
      "sessionId": "session-1756503305758-gix90yfiu",
      "type": "configuration_changed",
      "severity": "debug",
      "entity": "search",
      "action": "Tool registered",
      "triggeredBy": "system",
      "context": {
        "category": "discovery",
        "priority": 0
      }
    },
    {
      "id": "evt-1756503305805-v7zt1ierd",
      "timestamp": "2025-08-29T21:35:05.805Z",
      "sessionId": "session-1756503305758-gix90yfiu",
      "type": "configuration_changed",
      "severity": "debug",
      "entity": "project",
      "action": "Tool registered",
      "triggeredBy": "system",
      "context": {
        "category": "core-operations",
        "priority": 1
      }
    },
    {
      "id": "evt-1756503305805-65r872gf9",
      "timestamp": "2025-08-29T21:35:05.805Z",
      "sessionId": "session-1756503305758-gix90yfiu",
      "type": "configuration_changed",
      "severity": "debug",
      "entity": "studio",
      "action": "Tool registered",
      "triggeredBy": "system",
      "context": {
        "category": "core-operations",
        "priority": 2
      }
    },
    {
      "id": "evt-1756503305805-q4oa2imbj",
      "timestamp": "2025-08-29T21:35:05.805Z",
      "sessionId": "session-1756503305758-gix90yfiu",
      "type": "configuration_changed",
      "severity": "debug",
      "entity": "composition",
      "action": "Tool registered",
      "triggeredBy": "system",
      "context": {
        "category": "video-creation",
        "priority": 3
      }
    },
    {
      "id": "evt-1756503305805-ca8uzxawt",
      "timestamp": "2025-08-29T21:35:05.805Z",
      "sessionId": "session-1756503305758-gix90yfiu",
      "type": "configuration_changed",
      "severity": "debug",
      "entity": "dependencies",
      "action": "Tool registered",
      "triggeredBy": "system",
      "context": {
        "category": "maintenance",
        "priority": 4
      }
    },
    {
      "id": "evt-1756503305805-9hlogrc3s",
      "timestamp": "2025-08-29T21:35:05.805Z",
      "sessionId": "session-1756503305758-gix90yfiu",
      "type": "configuration_changed",
      "severity": "debug",
      "entity": "composition",
      "action": "Tool registered",
      "triggeredBy": "system",
      "context": {
        "category": "video-creation",
        "priority": 1
      }
    },
    {
      "id": "evt-1756503305806-9d5xieau9",
      "timestamp": "2025-08-29T21:35:05.806Z",
      "sessionId": "session-1756503305758-gix90yfiu",
      "type": "configuration_changed",
      "severity": "debug",
      "entity": "create-video",
      "action": "Tool registered",
      "triggeredBy": "system",
      "context": {
        "category": "video-creation",
        "priority": 1
      }
    },
    {
      "id": "evt-1756503305806-ohb5df9cv",
      "timestamp": "2025-08-29T21:35:05.806Z",
      "sessionId": "session-1756503305758-gix90yfiu",
      "type": "configuration_changed",
      "severity": "debug",
      "entity": "generate-assets",
      "action": "Tool registered",
      "triggeredBy": "system",
      "context": {
        "category": "asset-generation",
        "priority": 2
      }
    },
    {
      "id": "evt-1756503305806-f8rwgl6bs",
      "timestamp": "2025-08-29T21:35:05.806Z",
      "sessionId": "session-1756503305758-gix90yfiu",
      "type": "configuration_changed",
      "severity": "debug",
      "entity": "analyze-video",
      "action": "Tool registered",
      "triggeredBy": "system",
      "context": {
        "category": "video-creation",
        "priority": 3
      }
    },
    {
      "id": "evt-1756503305806-zir4u8cnn",
      "timestamp": "2025-08-29T21:35:05.806Z",
      "sessionId": "session-1756503305758-gix90yfiu",
      "type": "configuration_changed",
      "severity": "debug",
      "entity": "render",
      "action": "Tool registered",
      "triggeredBy": "system",
      "context": {
        "category": "video-creation",
        "priority": 4
      }
    },
    {
      "id": "evt-1756503305806-ztmr6eox3",
      "timestamp": "2025-08-29T21:35:05.806Z",
      "sessionId": "session-1756503305758-gix90yfiu",
      "type": "configuration_changed",
      "severity": "debug",
      "entity": "assets",
      "action": "Tool registered",
      "triggeredBy": "system",
      "context": {
        "category": "maintenance",
        "priority": 5
      }
    },
    {
      "id": "evt-1756503305806-110aasiox",
      "timestamp": "2025-08-29T21:35:05.806Z",
      "sessionId": "session-1756503305758-gix90yfiu",
      "type": "configuration_changed",
      "severity": "debug",
      "entity": "cache",
      "action": "Tool registered",
      "triggeredBy": "system",
      "context": {
        "category": "maintenance",
        "priority": 6
      }
    },
    {
      "id": "evt-1756503305806-n02powpgj",
      "timestamp": "2025-08-29T21:35:05.806Z",
      "sessionId": "session-1756503305758-gix90yfiu",
      "type": "configuration_changed",
      "severity": "debug",
      "entity": "voices",
      "action": "Tool registered",
      "triggeredBy": "system",
      "context": {
        "category": "voice-generation",
        "priority": 7
      }
    },
    {
      "id": "evt-1756503305806-td95b4g7x",
      "timestamp": "2025-08-29T21:35:05.806Z",
      "sessionId": "session-1756503305758-gix90yfiu",
      "type": "configuration_changed",
      "severity": "debug",
      "entity": "image-models",
      "action": "Tool registered",
      "triggeredBy": "system",
      "context": {
        "category": "image-generation",
        "priority": 8
      }
    },
    {
      "id": "evt-1756503305806-g6wc8m7ib",
      "timestamp": "2025-08-29T21:35:05.806Z",
      "sessionId": "session-1756503305758-gix90yfiu",
      "type": "configuration_changed",
      "severity": "debug",
      "entity": "sounds",
      "action": "Tool registered",
      "triggeredBy": "system",
      "context": {
        "category": "sound-effects",
        "priority": 9
      }
    }
  ],
  "statistics": {
    "totalEvents": 18,
    "eventsByType": {},
    "eventsBySeverity": {},
    "topEntities": [
      {
        "entity": "composition",
        "count": 2
      },
      {
        "entity": "system",
        "count": 1
      },
      {
        "entity": "discover",
        "count": 1
      },
      {
        "entity": "activate",
        "count": 1
      },
      {
        "entity": "search",
        "count": 1
      },
      {
        "entity": "project",
        "count": 1
      },
      {
        "entity": "studio",
        "count": 1
      },
      {
        "entity": "dependencies",
        "count": 1
      },
      {
        "entity": "create-video",
        "count": 1
      },
      {
        "entity": "generate-assets",
        "count": 1
      }
    ],
    "errorRate": 0,
    "averageDuration": 0,
    "peakPeriods": [
      {
        "hour": 0,
        "count": 18
      }
    ]
  },
  "patterns": []
}
